bekasi/__init__.py
bekasi-0.0.1.dist-info/DESCRIPTION.rst
bekasi-0.0.1.dist-info/METADATA
bekasi-0.0.1.dist-info/RECORD
bekasi-0.0.1.dist-info/WHEEL
bekasi-0.0.1.dist-info/metadata.json
bekasi-0.0.1.dist-info/top_level.txt
