Metadata-Version: 2.0
Name: bekasi
Version: 0.0.1
Summary: A small example package from Bekasi Indonesia
Home-page: https://github.com/randidwiputra/pip-bekasi
Author: randidwiputra
Author-email: randi.dwi.putra@gmail.com
License: UNKNOWN
Platform: UNKNOWN
Classifier: Programming Language :: Python :: 3
Classifier: License :: OSI Approved :: MIT License
Classifier: Operating System :: OS Independent
